esmlab/__init__.py
esmlab/common_utils.py
esmlab/config.py
esmlab/config.yaml
esmlab/core.py
esmlab/datasets.py
esmlab/regrid.py
esmlab/statistics.py
esmlab-2019.4.27.dist-info/LICENSE
esmlab-2019.4.27.dist-info/METADATA
esmlab-2019.4.27.dist-info/WHEEL
esmlab-2019.4.27.dist-info/top_level.txt
esmlab-2019.4.27.dist-info/RECORD
