Metadata-Version: 2.1
Name: esmlab
Version: 2019.4.27
Summary: Tools for working with earth system multi-model analyses with xarray
Home-page: https://github.com/NCAR/esmlab
Maintainer: Anderson Banihirwe
Maintainer-email: abanihi@ucar.edu
License: Apache License 2.0
Platform: UNKNOWN
Classifier: Development Status :: 4 - Beta
Classifier: License :: OSI Approved :: Apache Software License
Classifier: Operating System :: OS Independent
Classifier: Intended Audience :: Science/Research
Classifier: Programming Language :: Python
Classifier: Programming Language :: Python :: 3
Classifier: Programming Language :: Python :: 3.6
Classifier: Programming Language :: Python :: 3.7
Classifier: Topic :: Scientific/Engineering
Requires-Python: >3.5
Requires-Dist: bottleneck
Requires-Dist: cftime
Requires-Dist: dask
Requires-Dist: esmpy
Requires-Dist: netcdf4
Requires-Dist: pyyaml
Requires-Dist: scipy
Requires-Dist: xarray (>=0.11.2)
Requires-Dist: xesmf
